ngshare_exchange/__init__.py
ngshare_exchange/collect.py
ngshare_exchange/configure_exchange.py
ngshare_exchange/course_management.py
ngshare_exchange/exchange.py
ngshare_exchange/fetch_assignment.py
ngshare_exchange/fetch_feedback.py
ngshare_exchange/list.py
ngshare_exchange/release_assignment.py
ngshare_exchange/release_feedback.py
ngshare_exchange/submit.py
ngshare_exchange/version.py
ngshare_exchange/tests/__init__.py
ngshare_exchange/tests/base.py
ngshare_exchange/tests/test_collect.py
ngshare_exchange/tests/test_configure_exchange.py
ngshare_exchange/tests/test_course_management.py
ngshare_exchange/tests/test_exchange.py
ngshare_exchange/tests/test_fetch_assignment.py
ngshare_exchange/tests/test_fetch_feedback.py
ngshare_exchange/tests/test_list.py
ngshare_exchange/tests/test_release_assignment.py
ngshare_exchange/tests/test_release_feedback.py
ngshare_exchange/tests/test_submit.py
ngshare_exchange-0.5.3.dist-info/LICENSE
ngshare_exchange-0.5.3.dist-info/METADATA
ngshare_exchange-0.5.3.dist-info/WHEEL
ngshare_exchange-0.5.3.dist-info/entry_points.txt
ngshare_exchange-0.5.3.dist-info/top_level.txt
ngshare_exchange-0.5.3.dist-info/RECORD
