Metadata-Version: 2.1
Name: ngshare-exchange
Version: 0.5.3
Summary: nbgrader exchange to use with ngshare
Home-page: https://github.com/LibreTexts/ngshare_exchange
Author: Team KALE
Author-email: ercli@ucdavis.edu
Classifier: Programming Language :: Python :: 3
Classifier: License :: OSI Approved :: BSD License
Classifier: Operating System :: POSIX :: Linux
Requires-Python: >=3.7
License-File: LICENSE
Requires-Dist: rapidfuzz
Requires-Dist: traitlets
Requires-Dist: jupyter-core (<4.11.2)
Requires-Dist: nbgrader (>=0.7.0)
